odoo/addons/project_parent_task_filter/README.rst
odoo/addons/project_parent_task_filter/__init__.py
odoo/addons/project_parent_task_filter/__manifest__.py
odoo/addons/project_parent_task_filter/data/res_config_data.xml
odoo/addons/project_parent_task_filter/i18n/ca.po
odoo/addons/project_parent_task_filter/i18n/de.po
odoo/addons/project_parent_task_filter/i18n/es.po
odoo/addons/project_parent_task_filter/i18n/es_ES.po
odoo/addons/project_parent_task_filter/i18n/nl_NL.po
odoo/addons/project_parent_task_filter/i18n/project_parent_task_filter.pot
odoo/addons/project_parent_task_filter/readme/CONTRIBUTORS.rst
odoo/addons/project_parent_task_filter/readme/DESCRIPTION.rst
odoo/addons/project_parent_task_filter/readme/ROADMAP.rst
odoo/addons/project_parent_task_filter/readme/USAGE.rst
odoo/addons/project_parent_task_filter/static/description/icon.png
odoo/addons/project_parent_task_filter/static/description/index.html
odoo/addons/project_parent_task_filter/views/project_task.xml
odoo13_addon_project_parent_task_filter-13.0.1.1.0.dist-info/METADATA
odoo13_addon_project_parent_task_filter-13.0.1.1.0.dist-info/WHEEL
odoo13_addon_project_parent_task_filter-13.0.1.1.0.dist-info/top_level.txt
odoo13_addon_project_parent_task_filter-13.0.1.1.0.dist-info/RECORD
